sail_cameras/BaseCameraInterface.py
sail_cameras/__init__.py
sail_cameras/_modidx.py
sail_cameras/cameras.py
sail_cameras-0.0.2.dist-info/licenses/LICENSE
sail_cameras-0.0.2.dist-info/METADATA
sail_cameras-0.0.2.dist-info/WHEEL
sail_cameras-0.0.2.dist-info/entry_points.txt
sail_cameras-0.0.2.dist-info/top_level.txt
sail_cameras-0.0.2.dist-info/RECORD
